{"primaryContentSections":[{"kind":"declarations","declarations":[{"tokens":[{"kind":"attribute","text":"@objc"},{"kind":"text","text":" "},{"kind":"keyword","text":"static"},{"kind":"text","text":" "},{"kind":"keyword","text":"func"},{"kind":"text","text":" "},{"kind":"identifier","text":"xyzToRgb"},{"kind":"text","text":"("},{"kind":"externalParam","text":"xyzIn"},{"kind":"text","text":": "},{"kind":"typeIdentifier","text":"Array","preciseIdentifier":"s:Sa"},{"kind":"text","text":"<"},{"kind":"typeIdentifier","text":"Double","preciseIdentifier":"s:Sd"},{"kind":"text","text":">, "},{"kind":"externalParam","text":"refIn"},{"kind":"text","text":": "},{"kind":"typeIdentifier","text":"Array","preciseIdentifier":"s:Sa"},{"kind":"text","text":"<"},{"kind":"typeIdentifier","text":"Double","preciseIdentifier":"s:Sd"},{"kind":"text","text":">, "},{"kind":"externalParam","text":"rChrom"},{"kind":"text","text":": "},{"kind":"typeIdentifier","text":"Array","preciseIdentifier":"s:Sa"},{"kind":"text","text":"<"},{"kind":"typeIdentifier","text":"Double","preciseIdentifier":"s:Sd"},{"kind":"text","text":">, "},{"kind":"externalParam","text":"gChrom"},{"kind":"text","text":": "},{"kind":"typeIdentifier","text":"Array","preciseIdentifier":"s:Sa"},{"kind":"text","text":"<"},{"kind":"typeIdentifier","text":"Double","preciseIdentifier":"s:Sd"},{"kind":"text","text":">, "},{"kind":"externalParam","text":"bChrom"},{"kind":"text","text":": "},{"kind":"typeIdentifier","text":"Array","preciseIdentifier":"s:Sa"},{"kind":"text","text":"<"},{"kind":"typeIdentifier","text":"Double","preciseIdentifier":"s:Sd"},{"kind":"text","text":">, "},{"kind":"externalParam","text":"wChrom"},{"kind":"text","text":": "},{"kind":"typeIdentifier","text":"Array","preciseIdentifier":"s:Sa"},{"kind":"text","text":"<"},{"kind":"typeIdentifier","text":"Double","preciseIdentifier":"s:Sd"},{"kind":"text","text":">) -> "},{"kind":"typeIdentifier","text":"Array","preciseIdentifier":"s:Sa"},{"kind":"text","text":"<"},{"kind":"typeIdentifier","text":"Double","preciseIdentifier":"s:Sd"},{"kind":"text","text":">"}],"languages":["swift"],"platforms":["macOS"]}]},{"kind":"parameters","parameters":[{"name":"xyzIn","content":[{"type":"paragraph","inlineContent":[{"type":"text","text":"Input colour XYZ values, unity scale (element order X, Y, Z)"}]}]},{"name":"refIn","content":[{"type":"paragraph","inlineContent":[{"type":"text","text":"Reference white of input colour "},{"type":"codeVoice","code":"xyzIn"},{"type":"text","text":", unity scale (element order X, Y, Z)"}]}]},{"name":"rChrom","content":[{"type":"paragraph","inlineContent":[{"type":"text","text":"RGB space red primary chromaticity coordinates (element order x, y)"}]}]},{"name":"gChrom","content":[{"type":"paragraph","inlineContent":[{"type":"text","text":"RGB space green primary chromaticity coordinates (element order x, y)"}]}]},{"name":"bChrom","content":[{"type":"paragraph","inlineContent":[{"type":"text","text":"RGB space blue primary chromaticity coordinates (element order x, y)"}]}]},{"name":"wChrom","content":[{"type":"paragraph","inlineContent":[{"type":"text","text":"RGB space reference white\/grey chromaticity coordinates (element order x, y)"}]}]}]},{"kind":"content","content":[{"anchor":"return-value","level":2,"type":"heading","text":"Return Value"},{"type":"paragraph","inlineContent":[{"type":"text","text":"Linear RGB value, unity scale, (element order R, G, B)"}]}]}],"schemaVersion":{"major":0,"minor":3,"patch":0},"sections":[],"variants":[{"paths":["\/documentation\/nixuniversalsdk\/colorutils\/xyztorgb(xyzin:refin:rchrom:gchrom:bchrom:wchrom:)"],"traits":[{"interfaceLanguage":"swift"}]},{"paths":["\/documentation\/nixuniversalsdk\/colorutils\/xyztorgb(xyzin:refin:rchrom:gchrom:bchrom:wchrom:)"],"traits":[{"interfaceLanguage":"occ"}]}],"identifier":{"url":"doc:\/\/com.nixsensor.universalsdk\/documentation\/NixUniversalSDK\/ColorUtils\/xyzToRgb(xyzIn:refIn:rChrom:gChrom:bChrom:wChrom:)","interfaceLanguage":"swift"},"abstract":[{"type":"text","text":"Calculates linear RGB from XYZ given chromaticity coordinates of RGB working space primaries and reference whites of RGB and XYZ value"}],"kind":"symbol","metadata":{"fragments":[{"kind":"keyword","text":"static"},{"kind":"text","text":" "},{"kind":"keyword","text":"func"},{"kind":"text","text":" "},{"kind":"identifier","text":"xyzToRgb"},{"kind":"text","text":"("},{"kind":"externalParam","text":"xyzIn"},{"kind":"text","text":": "},{"kind":"typeIdentifier","text":"Array","preciseIdentifier":"s:Sa"},{"kind":"text","text":"<"},{"kind":"typeIdentifier","text":"Double","preciseIdentifier":"s:Sd"},{"kind":"text","text":">, "},{"kind":"externalParam","text":"refIn"},{"kind":"text","text":": "},{"kind":"typeIdentifier","text":"Array","preciseIdentifier":"s:Sa"},{"kind":"text","text":"<"},{"kind":"typeIdentifier","text":"Double","preciseIdentifier":"s:Sd"},{"kind":"text","text":">, "},{"kind":"externalParam","text":"rChrom"},{"kind":"text","text":": "},{"kind":"typeIdentifier","text":"Array","preciseIdentifier":"s:Sa"},{"kind":"text","text":"<"},{"kind":"typeIdentifier","text":"Double","preciseIdentifier":"s:Sd"},{"kind":"text","text":">, "},{"kind":"externalParam","text":"gChrom"},{"kind":"text","text":": "},{"kind":"typeIdentifier","text":"Array","preciseIdentifier":"s:Sa"},{"kind":"text","text":"<"},{"kind":"typeIdentifier","text":"Double","preciseIdentifier":"s:Sd"},{"kind":"text","text":">, "},{"kind":"externalParam","text":"bChrom"},{"kind":"text","text":": "},{"kind":"typeIdentifier","text":"Array","preciseIdentifier":"s:Sa"},{"kind":"text","text":"<"},{"kind":"typeIdentifier","text":"Double","preciseIdentifier":"s:Sd"},{"kind":"text","text":">, "},{"kind":"externalParam","text":"wChrom"},{"kind":"text","text":": "},{"kind":"typeIdentifier","text":"Array","preciseIdentifier":"s:Sa"},{"kind":"text","text":"<"},{"kind":"typeIdentifier","text":"Double","preciseIdentifier":"s:Sd"},{"kind":"text","text":">) -> "},{"kind":"typeIdentifier","text":"Array","preciseIdentifier":"s:Sa"},{"kind":"text","text":"<"},{"kind":"typeIdentifier","text":"Double","preciseIdentifier":"s:Sd"},{"kind":"text","text":">"}],"title":"xyzToRgb(xyzIn:refIn:rChrom:gChrom:bChrom:wChrom:)","roleHeading":"Type Method","role":"symbol","symbolKind":"method","externalID":"c:@M@NixUniversalSDK@objc(cs)ColorUtils(cm)xyzToRgbWithXyzIn:refIn:rChrom:gChrom:bChrom:wChrom:","modules":[{"name":"NixUniversalSDK"}],"navigatorTitle":[{"kind":"identifier","text":"xyzToRgbWithXyzIn:refIn:rChrom:gChrom:bChrom:wChrom:"}]},"hierarchy":{"paths":[["doc:\/\/com.nixsensor.universalsdk\/documentation\/NixUniversalSDK","doc:\/\/com.nixsensor.universalsdk\/documentation\/NixUniversalSDK\/ColorUtils"]]},"references":{"doc://com.nixsensor.universalsdk/documentation/NixUniversalSDK/ColorUtils":{"role":"symbol","title":"ColorUtils","fragments":[{"kind":"keyword","text":"class"},{"kind":"text","text":" "},{"kind":"identifier","text":"ColorUtils"}],"abstract":[{"type":"text","text":"Color math utility functions"}],"identifier":"doc:\/\/com.nixsensor.universalsdk\/documentation\/NixUniversalSDK\/ColorUtils","kind":"symbol","type":"topic","navigatorTitle":[{"kind":"identifier","text":"ColorUtils"}],"url":"\/documentation\/nixuniversalsdk\/colorutils"},"doc://com.nixsensor.universalsdk/documentation/NixUniversalSDK/ColorUtils/xyzToRgb(xyzIn:refIn:rChrom:gChrom:bChrom:wChrom:)":{"role":"symbol","title":"xyzToRgb(xyzIn:refIn:rChrom:gChrom:bChrom:wChrom:)","fragments":[{"kind":"keyword","text":"static"},{"kind":"text","text":" "},{"kind":"keyword","text":"func"},{"kind":"text","text":" "},{"kind":"identifier","text":"xyzToRgb"},{"kind":"text","text":"("},{"kind":"externalParam","text":"xyzIn"},{"kind":"text","text":": "},{"kind":"typeIdentifier","text":"Array","preciseIdentifier":"s:Sa"},{"kind":"text","text":"<"},{"kind":"typeIdentifier","text":"Double","preciseIdentifier":"s:Sd"},{"kind":"text","text":">, "},{"kind":"externalParam","text":"refIn"},{"kind":"text","text":": "},{"kind":"typeIdentifier","text":"Array","preciseIdentifier":"s:Sa"},{"kind":"text","text":"<"},{"kind":"typeIdentifier","text":"Double","preciseIdentifier":"s:Sd"},{"kind":"text","text":">, "},{"kind":"externalParam","text":"rChrom"},{"kind":"text","text":": "},{"kind":"typeIdentifier","text":"Array","preciseIdentifier":"s:Sa"},{"kind":"text","text":"<"},{"kind":"typeIdentifier","text":"Double","preciseIdentifier":"s:Sd"},{"kind":"text","text":">, "},{"kind":"externalParam","text":"gChrom"},{"kind":"text","text":": "},{"kind":"typeIdentifier","text":"Array","preciseIdentifier":"s:Sa"},{"kind":"text","text":"<"},{"kind":"typeIdentifier","text":"Double","preciseIdentifier":"s:Sd"},{"kind":"text","text":">, "},{"kind":"externalParam","text":"bChrom"},{"kind":"text","text":": "},{"kind":"typeIdentifier","text":"Array","preciseIdentifier":"s:Sa"},{"kind":"text","text":"<"},{"kind":"typeIdentifier","text":"Double","preciseIdentifier":"s:Sd"},{"kind":"text","text":">, "},{"kind":"externalParam","text":"wChrom"},{"kind":"text","text":": "},{"kind":"typeIdentifier","text":"Array","preciseIdentifier":"s:Sa"},{"kind":"text","text":"<"},{"kind":"typeIdentifier","text":"Double","preciseIdentifier":"s:Sd"},{"kind":"text","text":">) -> "},{"kind":"typeIdentifier","text":"Array","preciseIdentifier":"s:Sa"},{"kind":"text","text":"<"},{"kind":"typeIdentifier","text":"Double","preciseIdentifier":"s:Sd"},{"kind":"text","text":">"}],"abstract":[{"type":"text","text":"Calculates linear RGB from XYZ given chromaticity coordinates of RGB working space primaries and reference whites of RGB and XYZ value"}],"identifier":"doc:\/\/com.nixsensor.universalsdk\/documentation\/NixUniversalSDK\/ColorUtils\/xyzToRgb(xyzIn:refIn:rChrom:gChrom:bChrom:wChrom:)","kind":"symbol","type":"topic","navigatorTitle":[{"kind":"identifier","text":"xyzToRgbWithXyzIn:refIn:rChrom:gChrom:bChrom:wChrom:"}],"url":"\/documentation\/nixuniversalsdk\/colorutils\/xyztorgb(xyzin:refin:rchrom:gchrom:bchrom:wchrom:)"},"doc://com.nixsensor.universalsdk/documentation/NixUniversalSDK":{"role":"collection","title":"NixUniversalSDK","abstract":[{"type":"text","text":"A framework to allow integration of Nix devices into third party iOS and macOS applications."}],"identifier":"doc:\/\/com.nixsensor.universalsdk\/documentation\/NixUniversalSDK","kind":"symbol","type":"topic","url":"\/documentation\/nixuniversalsdk"}},"variantOverrides":[{"patch":[{"op":"replace","path":"\/identifier\/interfaceLanguage","value":"occ"},{"op":"replace","path":"\/metadata\/roleHeading","value":"Type Method"},{"op":"replace","path":"\/metadata\/title","value":"xyzToRgbWithXyzIn:refIn:rChrom:gChrom:bChrom:wChrom:"},{"op":"replace","path":"\/metadata\/symbolKind","value":"method"},{"op":"replace","path":"\/metadata\/fragments","value":[{"kind":"text","text":"+ "},{"kind":"identifier","text":"xyzToRgbWithXyzIn:refIn:rChrom:gChrom:bChrom:wChrom:"}]},{"op":"add","path":"\/topicSections","value":null},{"op":"add","path":"\/relationshipsSections","value":null},{"op":"add","path":"\/seeAlsoSections","value":null},{"op":"replace","path":"\/primaryContentSections\/0","value":{"kind":"declarations","declarations":[{"tokens":[{"kind":"text","text":"+ ("},{"kind":"typeIdentifier","text":"NSArray<NSNumber *>","preciseIdentifier":"c:Q$objc(cs)NSArray"},{"kind":"text","text":" *) "},{"kind":"identifier","text":"xyzToRgbWithXyzIn:"},{"kind":"text","text":"("},{"kind":"typeIdentifier","text":"NSArray<NSNumber *>","preciseIdentifier":"c:Q$objc(cs)NSArray"},{"kind":"text","text":" *) "},{"kind":"internalParam","text":"xyzIn"},{"kind":"text","text":" "},{"kind":"identifier","text":"refIn:"},{"kind":"text","text":"("},{"kind":"typeIdentifier","text":"NSArray<NSNumber *>","preciseIdentifier":"c:Q$objc(cs)NSArray"},{"kind":"text","text":" *) "},{"kind":"internalParam","text":"refIn"},{"kind":"text","text":" "},{"kind":"identifier","text":"rChrom:"},{"kind":"text","text":"("},{"kind":"typeIdentifier","text":"NSArray<NSNumber *>","preciseIdentifier":"c:Q$objc(cs)NSArray"},{"kind":"text","text":" *) "},{"kind":"internalParam","text":"rChrom"},{"kind":"text","text":" "},{"kind":"identifier","text":"gChrom:"},{"kind":"text","text":"("},{"kind":"typeIdentifier","text":"NSArray<NSNumber *>","preciseIdentifier":"c:Q$objc(cs)NSArray"},{"kind":"text","text":" *) "},{"kind":"internalParam","text":"gChrom"},{"kind":"text","text":" "},{"kind":"identifier","text":"bChrom:"},{"kind":"text","text":"("},{"kind":"typeIdentifier","text":"NSArray<NSNumber *>","preciseIdentifier":"c:Q$objc(cs)NSArray"},{"kind":"text","text":" *) "},{"kind":"internalParam","text":"bChrom"},{"kind":"text","text":" "},{"kind":"identifier","text":"wChrom:"},{"kind":"text","text":"("},{"kind":"typeIdentifier","text":"NSArray<NSNumber *>","preciseIdentifier":"c:Q$objc(cs)NSArray"},{"kind":"text","text":" *) "},{"kind":"internalParam","text":"wChrom"},{"kind":"text","text":";"}],"languages":["occ"],"platforms":["macOS"]}]}},{"op":"replace","path":"\/references\/doc:~1~1com.nixsensor.universalsdk~1documentation~1NixUniversalSDK~1ColorUtils\/title","value":"ColorUtils"},{"op":"replace","path":"\/references\/doc:~1~1com.nixsensor.universalsdk~1documentation~1NixUniversalSDK~1ColorUtils\/fragments","value":[{"kind":"identifier","text":"ColorUtils"}]},{"op":"replace","path":"\/references\/doc:~1~1com.nixsensor.universalsdk~1documentation~1NixUniversalSDK~1ColorUtils~1xyzToRgb(xyzIn:refIn:rChrom:gChrom:bChrom:wChrom:)\/title","value":"xyzToRgbWithXyzIn:refIn:rChrom:gChrom:bChrom:wChrom:"},{"op":"replace","path":"\/references\/doc:~1~1com.nixsensor.universalsdk~1documentation~1NixUniversalSDK~1ColorUtils~1xyzToRgb(xyzIn:refIn:rChrom:gChrom:bChrom:wChrom:)\/fragments","value":[{"kind":"text","text":"+ "},{"kind":"identifier","text":"xyzToRgbWithXyzIn:refIn:rChrom:gChrom:bChrom:wChrom:"}]}],"traits":[{"interfaceLanguage":"occ"}]}]}